cttest_plus/__init__.py
cttest_plus/_miracle.py
cttest_plus/cli.py
cttest_plus/globalSetting.py
cttest_plus/run.py
cttest_plus/testFactory.py
cttest_plus/_locust/__init__.py
cttest_plus/_locust/httpDriver.py
cttest_plus/_locust/locustfile.py
cttest_plus/assert_/__init__.py
cttest_plus/assert_/app.py
cttest_plus/assert_/comparetors.py
cttest_plus/assert_/jsonFormAssert.py
cttest_plus/assert_/publicAssert.py
cttest_plus/assert_/web.py
cttest_plus/cjstest/__init__.py
cttest_plus/cjstest/hookimpl.py
cttest_plus/cjstest/locustManage.py
cttest_plus/cjstest/manage.py
cttest_plus/cjstest/miracle.py
cttest_plus/cjstest/run.py
cttest_plus/cjstest/settings.py
cttest_plus/cjstest/kword/__init__.py
cttest_plus/cjstest/test_case/__init__.py
cttest_plus/cjstest/test_case/test_v1.py
cttest_plus/cjstest/tool/__init__.py
cttest_plus/cjstest/tool/model.py
cttest_plus/cjstest/tool/mysqlController.py
cttest_plus/cjstest/tool/step.py
cttest_plus/core/__init__.py
cttest_plus/core/locustLoader.py
cttest_plus/core/nodeParser.py
cttest_plus/core/pytestLoader.py
cttest_plus/drivers/__init__.py
cttest_plus/drivers/appDriver.py
cttest_plus/drivers/basicDriver.py
cttest_plus/drivers/compatorDriver.py
cttest_plus/drivers/debugDriver.py
cttest_plus/drivers/driverBy.py
cttest_plus/drivers/httpDriver.py
cttest_plus/drivers/kwDriver.py
cttest_plus/drivers/locustDriver.py
cttest_plus/drivers/webDriver.py
cttest_plus/sessionManage/__init__.py
cttest_plus/sessionManage/baseSession.py
cttest_plus/sessionManage/locustHttpSession.py
cttest_plus/sessionManage/requestsSession.py
cttest_plus/sessionManage/appSession/__init__.py
cttest_plus/sessionManage/appSession/appiumSession.py
cttest_plus/sessionManage/appSession/devicesManage.py
cttest_plus/sessionManage/appSession/element.py
cttest_plus/sessionManage/appSession/openstfController.py
cttest_plus/sessionManage/webSession/__init__.py
cttest_plus/sessionManage/webSession/element.py
cttest_plus/sessionManage/webSession/seleniumSession.py
cttest_plus-1.3.27.dist-info/METADATA
cttest_plus-1.3.27.dist-info/WHEEL
cttest_plus-1.3.27.dist-info/entry_points.txt
cttest_plus-1.3.27.dist-info/top_level.txt
cttest_plus-1.3.27.dist-info/RECORD
