Metadata-Version: 2.1
Name: cttest_plus
Version: 1.3.27
Home-page: https://gitlab.casstime.net/qa/TestArchitecture/cttest2
Author: ZhiXiaoGongChengBu
Author-email: 
License: MIT
Requires-Dist: requests
Requires-Dist: har2case
Requires-Dist: openpyxl
Requires-Dist: pyyaml
Requires-Dist: selenium
Requires-Dist: pytest
Requires-Dist: allure-pytest
Requires-Dist: pymysql
Requires-Dist: paramiko
Requires-Dist: faker
Requires-Dist: jmespath
Requires-Dist: Appium-Python-Client
Requires-Dist: lxml
Requires-Dist: moviepy
Requires-Dist: pytest-rerunfailures
Requires-Dist: parsel
Requires-Dist: loguru
Requires-Dist: pandas
Requires-Dist: suds
Requires-Dist: redis
